test/__init__.py
test/conftest.py
test/test_core.py
test/test_inspect.py
test/test_orm.py
test/test_suite.py
ydb_sqlalchemy/__init__.py
ydb_sqlalchemy/_version.py
ydb_sqlalchemy/sqlalchemy/__init__.py
ydb_sqlalchemy/sqlalchemy/datetime_types.py
ydb_sqlalchemy/sqlalchemy/dbapi_adapter.py
ydb_sqlalchemy/sqlalchemy/dml.py
ydb_sqlalchemy/sqlalchemy/json.py
ydb_sqlalchemy/sqlalchemy/requirements.py
ydb_sqlalchemy/sqlalchemy/test_sqlalchemy.py
ydb_sqlalchemy/sqlalchemy/types.py
ydb_sqlalchemy/sqlalchemy/compiler/__init__.py
ydb_sqlalchemy/sqlalchemy/compiler/base.py
ydb_sqlalchemy/sqlalchemy/compiler/sa14.py
ydb_sqlalchemy/sqlalchemy/compiler/sa20.py
ydb_sqlalchemy-0.1.15.dist-info/LICENSE
ydb_sqlalchemy-0.1.15.dist-info/METADATA
ydb_sqlalchemy-0.1.15.dist-info/WHEEL
ydb_sqlalchemy-0.1.15.dist-info/entry_points.txt
ydb_sqlalchemy-0.1.15.dist-info/top_level.txt
ydb_sqlalchemy-0.1.15.dist-info/RECORD
