Metadata-Version: 2.1
Name: ydb-sqlalchemy
Version: 0.1.15
Summary: YDB Dialect for SQLAlchemy
Home-page: http://github.com/ydb-platform/ydb-sqlalchemy
Author: Yandex LLC
Author-email: ydb@yandex-team.ru
License: Apache 2.0
Keywords: SQLAlchemy YDB YQL
Classifier: Programming Language :: Python
Classifier: Programming Language :: Python :: 3
Classifier: Programming Language :: Python :: 3.8
License-File: LICENSE
Requires-Dist: sqlalchemy <3.0.0,>=1.4.0
Requires-Dist: ydb >=3.21.6
Requires-Dist: ydb-dbapi >=0.1.16
Provides-Extra: yc
Requires-Dist: yandexcloud ; extra == 'yc'
